setup.py
bmi_calculate_test/__init__.py
bmi_calculate_test/bmi_calculate_test.py
bmi_calculate_test.egg-info/PKG-INFO
bmi_calculate_test.egg-info/SOURCES.txt
bmi_calculate_test.egg-info/dependency_links.txt
bmi_calculate_test.egg-info/not-zip-safe
bmi_calculate_test.egg-info/top_level.txt