Metadata-Version: 2.1
Name: bmi-calculate-test
Version: 0.1
Summary: Calculate BMI
Home-page: UNKNOWN
Author: kennedy wambua
License: UNKNOWN
Platform: UNKNOWN
